keras4torch/__init__.py
keras4torch/_custom_training.py
keras4torch/_training.py
keras4torch/activations.py
keras4torch/callbacks.py
keras4torch/configs.py
keras4torch/hub.py
keras4torch/losses.py
keras4torch/metrics.py
keras4torch/optimizers.py
keras4torch/_summary/__init__.py
keras4torch/_summary/formatting.py
keras4torch/_summary/layer_info.py
keras4torch/_summary/model_statistics.py
keras4torch/_summary/torchsummary.py
keras4torch/layers/__init__.py
keras4torch/layers/_keras_layers.py
keras4torch/layers/_util_layers.py
keras4torch/layers/se_net.py
keras4torch/models/__init__.py
keras4torch/models/_wrapper.py
keras4torch/utils/__init__.py
keras4torch/utils/_keras_progress_bar.py
keras4torch/utils/_to_tensor.py
keras4torch/utils/data.py
keras4torch-1.2.4.dist-info/LICENSE
keras4torch-1.2.4.dist-info/METADATA
keras4torch-1.2.4.dist-info/WHEEL
keras4torch-1.2.4.dist-info/top_level.txt
keras4torch-1.2.4.dist-info/RECORD
