Metadata-Version: 2.1
Name: keras4torch
Version: 1.2.4
Summary: A compatible-with-keras wrapper for training PyTorch models✨
Home-page: https://github.com/blueloveTH/keras4torch
Author: blueloveTH
Author-email: blueloveTH@qq.com
License: UNKNOWN
Platform: UNKNOWN
Classifier: Programming Language :: Python :: 3
Classifier: License :: OSI Approved :: MIT License
Classifier: Operating System :: OS Independent
Requires-Python: >=3.6
Requires-Dist: pandas
